inventoryctl/__init__.py
inventoryctl/main.py
inventoryctl/commands/__init__.py
inventoryctl/commands/add.py
inventoryctl/commands/batch.py
inventoryctl/commands/delete.py
inventoryctl/commands/format_cmd.py
inventoryctl/commands/get.py
inventoryctl/commands/list_cmd.py
inventoryctl/commands/render.py
inventoryctl/commands/sync.py
inventoryctl/commands/update.py
inventoryctl/commands/validate.py
inventoryctl/core/__init__.py
inventoryctl/core/errors.py
inventoryctl/core/yaml_handler.py
inventoryctl-0.2.0.dist-info/METADATA
inventoryctl-0.2.0.dist-info/WHEEL
inventoryctl-0.2.0.dist-info/entry_points.txt
inventoryctl-0.2.0.dist-info/top_level.txt
inventoryctl-0.2.0.dist-info/RECORD
