Metadata-Version: 2.4
Name: inventoryctl
Version: 0.2.0
Summary: A CLI tool for managing inventory YAML files
Author: aabichou
License: MIT
Requires-Python: >=3.8
Requires-Dist: typer>=0.9.0
Requires-Dist: ruamel.yaml>=0.17.0
Requires-Dist: pydantic>=2.0.0
